cepan/__init__.py
cepan/_alias.py
cepan/_cost_and_usage.py
cepan/_dimension.py
cepan/_filter.py
cepan/_group_by.py
cepan/_sort_by.py
cepan/_tag.py
cepan/_time_period.py
cepan/_utils.py
cepan/exceptions.py
cepan-0.2.0.dist-info/LICENSE
cepan-0.2.0.dist-info/WHEEL
cepan-0.2.0.dist-info/METADATA
cepan-0.2.0.dist-info/RECORD
