Metadata-Version: 2.1
Name: cepan
Version: 0.2.0
Summary: Retrieves data from aws cost explore as a pandas dataframe.
Home-page: https://github.com/kanga333/cepan
License: MIT
Author: kanga333
Author-email: e411z7t40w@gmail.com
Requires-Python: >=3.8,<4.0
Classifier: Development Status :: 3 - Alpha
Classifier: Environment :: Console
Classifier: Intended Audience :: Developers
Classifier: Intended Audience :: System Administrators
Classifier: License :: OSI Approved :: MIT License
Classifier: Programming Language :: Python :: 3
Classifier: Programming Language :: Python :: 3.8
Classifier: Programming Language :: Python :: 3.9
Requires-Dist: boto3 (>=1.17.19,<2.0.0)
Requires-Dist: pandas (>=1.2.3,<2.0.0)
Project-URL: Repository, https://github.com/kanga333/cepan
